skrutable/__init__.py
skrutable/config.json
skrutable/config.py
skrutable/manual.md
skrutable/meter_identification.py
skrutable/meter_patterns.py
skrutable/phonemes.py
skrutable/scansion.py
skrutable/scheme_detection.py
skrutable/scheme_maps.py
skrutable/scheme_vectors_mbh.py
skrutable/splitting.py
skrutable/transliteration.py
skrutable/virAma_avoidance.py
skrutable-2.0.7.dist-info/LICENSE.md
skrutable-2.0.7.dist-info/METADATA
skrutable-2.0.7.dist-info/WHEEL
skrutable-2.0.7.dist-info/top_level.txt
skrutable-2.0.7.dist-info/RECORD
